README.md
setup.py
esender/__init__.py
esender.egg-info/PKG-INFO
esender.egg-info/SOURCES.txt
esender.egg-info/dependency_links.txt
esender.egg-info/not-zip-safe
esender.egg-info/requires.txt
esender.egg-info/top_level.txt