Metadata-Version: 1.0
Name: esender
Version: 0.1.1
Summary: send email for notification
Home-page: https://github.com/jiesihu/esender
Author: Jiesi
Author-email: jiesihu@usc.com
License: MIT
Platform: UNKNOWN
